pyvariantfilter/__init__.py
pyvariantfilter/family.py
pyvariantfilter/family_member.py
pyvariantfilter/utils.py
pyvariantfilter/variant.py
pyvariantfilter/variant_set.py
pyvariantfilter/wrappers.py
pyvariantfilter-3.0.1.dist-info/METADATA
pyvariantfilter-3.0.1.dist-info/WHEEL
pyvariantfilter-3.0.1.dist-info/top_level.txt
pyvariantfilter-3.0.1.dist-info/RECORD
