Metadata-Version: 2.1
Name: pyvariantfilter
Version: 3.0.1
Summary: Python package for filtering variants.
Home-page: https://github.com/josephhalstead/pyvariantfilter
Author: Joseph Halstead
Author-email: josephhalstead89@gmail.com
Classifier: Programming Language :: Python :: 3
Classifier: Operating System :: OS Independent
Requires-Dist: pysam (>=0.22.1)
Requires-Dist: pandas (>=2.2)
